celerite2/terms.py
celerite2/citation.py
celerite2/driver.cpython-312-darwin.so
celerite2/driver.hpp
celerite2/__init__.py
celerite2/core.py
celerite2/numpy.py
celerite2/backprop.cpython-312-darwin.so
celerite2/driver.cpp
celerite2/backprop.cpp
celerite2/celerite2_version.py
celerite2/definitions.json
celerite2/testing.py
celerite2/pymc/terms.py
celerite2/pymc/__init__.py
celerite2/pymc/distribution.py
celerite2/pymc/ops.py
celerite2/pymc/celerite2.py
celerite2/pymc/jax_support.py
celerite2/theano/terms.py
celerite2/theano/__init__.py
celerite2/jax/terms.py
celerite2/jax/xla_ops.cpp
celerite2/jax/__init__.py
celerite2/jax/distribution.py
celerite2/jax/ops.py
celerite2/jax/celerite2.py
celerite2/jax/xla_ops.cpython-312-darwin.so
celerite2/pymc3/terms.py
celerite2/pymc3/__init__.py
celerite2/pymc3/distribution.py
celerite2/pymc3/ops.py
celerite2/pymc3/celerite2.py
celerite2-0.3.2.dist-info/RECORD
celerite2-0.3.2.dist-info/WHEEL
celerite2-0.3.2.dist-info/METADATA
celerite2-0.3.2.dist-info/licenses/LICENSE
