Metadata-Version: 2.1
Name: celerite2
Version: 0.3.2
Summary: Fast and scalable Gaussian Processes in 1D
Author-Email: Dan Foreman-Mackey <foreman.mackey@gmail.com>
License: MIT License
Classifier: Development Status :: 4 - Beta
Classifier: Intended Audience :: Developers
Classifier: Intended Audience :: Science/Research
Classifier: License :: OSI Approved :: MIT License
Classifier: Operating System :: OS Independent
Classifier: Programming Language :: Python
Project-URL: Homepage, https://celerite2.readthedocs.io
Project-URL: Source, https://github.com/exoplanet-dev/celerite2
Project-URL: Bug tracker, https://github.com/exoplanet-dev/celerite2/issues
Requires-Python: >=3.9
Requires-Dist: numpy
Requires-Dist: pytest; extra == "test"
Requires-Dist: scipy; extra == "test"
Requires-Dist: celerite; extra == "test"
Requires-Dist: pymc3>=3.9; extra == "pymc3"
Requires-Dist: numpy<1.22; extra == "pymc3"
Requires-Dist: xarray<2023.10.0; extra == "pymc3"
Requires-Dist: pymc3>=3.9; extra == "theano"
Requires-Dist: numpy<1.22; extra == "theano"
Requires-Dist: xarray<2023.10.0; extra == "theano"
Requires-Dist: pymc>=5.9.2; extra == "pymc"
Requires-Dist: jax; extra == "jax"
Requires-Dist: sphinx; extra == "docs"
Requires-Dist: sphinx-material; extra == "docs"
Requires-Dist: sphinx_copybutton; extra == "docs"
Requires-Dist: breathe; extra == "docs"
Requires-Dist: myst-nb; extra == "docs"
Requires-Dist: matplotlib; extra == "docs"
Requires-Dist: scipy; extra == "docs"
Requires-Dist: emcee; extra == "docs"
Requires-Dist: pymc>=5; extra == "docs"
Requires-Dist: tqdm; extra == "docs"
Requires-Dist: numpyro; extra == "docs"
Requires-Dist: matplotlib; extra == "tutorials"
Requires-Dist: scipy; extra == "tutorials"
Requires-Dist: emcee; extra == "tutorials"
Requires-Dist: pymc>=5; extra == "tutorials"
Requires-Dist: tqdm; extra == "tutorials"
Requires-Dist: numpyro; extra == "tutorials"
Provides-Extra: test
Provides-Extra: pymc3
Provides-Extra: theano
Provides-Extra: pymc
Provides-Extra: jax
Provides-Extra: docs
Provides-Extra: tutorials
